{
  "version": "1.22.0",
  "versionCode": 74,
  "channel": "apk",
  "updateMode": "in_app_apk",
  "minVersion": "1.0.0",
  "minVersionCode": 1,
  "mandatory": false,
  "updateType": "full",
  "network": "mainnet",
  "chainId": 72010,
  "apkUrl": "https://verdexswap.site/assets/downloads/Verdex-Android-1.22.0-build74.apk",
  "sha256": "367bffa1a811b1f5cbedb900a9f0538945fc7053bb60fcead393d9b160d217ba",
  "changelog": [
    "NEW: Full platform overhaul release (Build 74)",
    "FIXED: KYC submission case_id auto-resolution and direct profile image processing",
    "FIXED: Profile picture upload invalid address error resolved",
    "NEW: User UID display badge under profile with instant tap-to-copy",
    "FIXED: Vault deposit address copy button & QR code rendering",
    "FIXED: P2P trade creation custodial wallet lookup fallback",
    "NEW: Master Web Admin Panel with P2P Orders, Trades, Wallets, KYC & Health modules"
  ],
  "releasedAt": "2026-07-21T22:55:00.000Z"
}
